azure_datastore_utils/__init__.py
azure_datastore_utils/ai_search_utils.py
azure_datastore_utils/ai_search_utils_async.py
azure_datastore_utils/cosmos_db_utils.py
azure_datastore_utils/cosmos_db_utils_async.py
azure_datastore_utils/redis_util.py
azure_datastore_utils/redis_utils_async.py
azure_datastore_utils-0.2.4.dist-info/METADATA
azure_datastore_utils-0.2.4.dist-info/WHEEL
azure_datastore_utils-0.2.4.dist-info/licenses/LICENSE
azure_datastore_utils-0.2.4.dist-info/RECORD
