Metadata-Version: 2.4
Name: azure-datastore-utils
Version: 0.2.4
Summary: A collection of helper/wrapper utilities to interact with certain Azure data stores
Project-URL: Homepage, https://github.com/projectAcetylcholine/azure-datastore-utils
Project-URL: Source, https://github.com/projectAcetylcholine/azure-datastore-utils
Project-URL: Documentation, https://github.com/projectAcetylcholine/azure-datastore-utils/blob/main/README.md
Project-URL: Changelog, https://github.com/projectAcetylcholine/azure-datastore-utils/blob/main/README.md
Author-email: Israel Ekpo <israel@izzyacademy.ai>
License-File: LICENSE
Requires-Python: >=3.12
Requires-Dist: aiohttp>=3.12.15
Requires-Dist: azure-core~=1.34.0
Requires-Dist: azure-cosmos==4.9.0
Requires-Dist: azure-identity
Requires-Dist: azure-search-documents>=11.5.2
Requires-Dist: certifi>=2025.8.3
Requires-Dist: hatchling>=1.27.0
Requires-Dist: pydantic>=2.11.7
Requires-Dist: redis
Requires-Dist: redis-entraid
Requires-Dist: uv-dynamic-versioning>=0.11.0
